[{"meeting_cd":"C6502005022313301","committee":"Veteran Affairs & Military Installations Committee","dttm":"February 23, 2005 - 1:30P","session":"","bill_name":"","bill_cd":"","position":"","rbnt":false,"self":false,"fullWitnessName":"Adjutant General's Department      ON:         Dehnert, Brig. Gen. Allen Assistant Adjutant General\r","given_name":"Brig. Gen. Allen Assistant Adjutant General","sur_name":"Adjutant General's Department ON: Dehnert","organization":"","error":true},{"meeting_cd":"C6502005022313301","committee":"Veteran Affairs & Military Installations Committee","dttm":"February 23, 2005 - 1:30P","session":"","bill_name":"","bill_cd":"","position":"","rbnt":false,"self":false,"fullWitnessName":"ON:         Dehnert, Brig. Gen. Allen Assistant Adjutant General                         (Adjutant General's Department), Austin, TX\r","given_name":"Brig. Gen. Allen Assistant Adjutant General , Austin, TX","sur_name":"ON: Dehnert","organization":"Adjutant General's Department","error":false},{"meeting_cd":"C6502005022313301","committee":"Veteran Affairs & Military Installations Committee","dttm":"February 23, 2005 - 1:30P","session":"","bill_name":"","bill_cd":"","position":"","rbnt":false,"self":false,"fullWitnessName":"Family Readiness Program      ON:         Marty, Janie (Adjutant General's Department),\r","given_name":"Janie ,","sur_name":"Family Readiness Program ON: Marty","organization":"Adjutant General's Department","error":false},{"meeting_cd":"C6502005022313301","committee":"Veteran Affairs & Military Installations Committee","dttm":"February 23, 2005 - 1:30P","session":"","bill_name":"","bill_cd":"","position":"","rbnt":false,"self":false,"fullWitnessName":"Austin, TX                  Scotti, LTC  Sharon (Adjutant General's Department),\r","given_name":"TX Scotti, LTC Sharon ,","sur_name":"Austin","organization":"Adjutant General's Department","error":false},{"meeting_cd":"C6502005022313301","committee":"Veteran Affairs & Military Installations Committee","dttm":"February 23, 2005 - 1:30P","session":"","bill_name":"","bill_cd":"","position":"","rbnt":false,"self":false,"fullWitnessName":"Austin, TX\r","given_name":"TX","sur_name":"Austin","organization":"","error":true},{"meeting_cd":"C6502005022313301","committee":"Veteran Affairs & Military Installations Committee","dttm":"February 23, 2005 - 1:30P","session":"","bill_name":"","bill_cd":"","position":"","rbnt":false,"self":false,"fullWitnessName":"Texas Military Facilities Commission      ON:         Paret, Sandra M. Chair (Texas Military Facilities\r","given_name":"(Texas Military Facilities","sur_name":"","organization":"exas Military Facilities Commission ON: Paret, Sandra M. Chair","error":true},{"meeting_cd":"C6502005022313301","committee":"Veteran Affairs & Military Installations Committee","dttm":"February 23, 2005 - 1:30P","session":"","bill_name":"","bill_cd":"","position":"","rbnt":false,"self":false,"fullWitnessName":"ON:         Paret, Sandra M. Chair (Texas Military Facilities                         Commission), Austin, TX\r","given_name":"Sandra M. Chair , Austin, TX","sur_name":"ON: Paret","organization":"Texas Military Facilities Commission","error":false},{"meeting_cd":"C6502005022313301","committee":"Veteran Affairs & Military Installations Committee","dttm":"February 23, 2005 - 1:30P","session":"","bill_name":"","bill_cd":"","position":"","rbnt":false,"self":false,"fullWitnessName":"Wells, John Executive Director (Texas Military                         Facilities Commission), Austin, TX\r","given_name":"John Executive Director , Austin, TX","sur_name":"Wells","organization":"Texas Military Facilities Commission","error":false},{"meeting_cd":"C6502005022313301","committee":"Veteran Affairs & Military Installations Committee","dttm":"February 23, 2005 - 1:30P","session":"","bill_name":"","bill_cd":"","position":"On","rbnt":true,"self":false,"fullWitnessName":"Giesbers, Lydia Deputy Director (Texas Military                         Facilities Commission), Austin, TX\r","given_name":"Lydia Deputy Director , Austin, TX","sur_name":"Giesbers","organization":"Texas Military Facilities Commission","error":false}]