[{"meeting_cd":"C3202001042310301","committee":"Insurance Committee","dttm":"April 23, 2001-10:30A","session":"77R","bill_name":"HB 955","bill_cd":"HB955","position":"For","rbnt":false,"self":true,"fullWitnessName":"Day, Donald (Self)","given_name":"Donald","sur_name":"Day","organization":"","error":false},{"meeting_cd":"C3202001042310301","committee":"Insurance Committee","dttm":"April 23, 2001-10:30A","session":"77R","bill_name":"HB 955","bill_cd":"HB955","position":"For","rbnt":false,"self":false,"fullWitnessName":"Lloyd, Chuck (Texas Glass and Tinting)","given_name":"Chuck","sur_name":"Lloyd","organization":"Texas Glass and Tinting","error":false},{"meeting_cd":"C3202001042310301","committee":"Insurance Committee","dttm":"April 23, 2001-10:30A","session":"77R","bill_name":"HB 955","bill_cd":"HB955","position":"For","rbnt":false,"self":true,"fullWitnessName":"Smalley, Roy (Self and Texas Lone Star Collision                   Association)\r","given_name":"Roy","sur_name":"Smalley","organization":"and Texas Lone Star Collision Association","error":false},{"meeting_cd":"C3202001042310301","committee":"Insurance Committee","dttm":"April 23, 2001-10:30A","session":"77R","bill_name":"HB 955","bill_cd":"HB955","position":"For","rbnt":false,"self":false,"fullWitnessName":"Walden, James (Direct Appraisal)","given_name":"James","sur_name":"Walden","organization":"Direct Appraisal","error":false},{"meeting_cd":"C3202001042310301","committee":"Insurance Committee","dttm":"April 23, 2001-10:30A","session":"77R","bill_name":"HB 955","bill_cd":"HB955","position":"Against","rbnt":false,"self":false,"fullWitnessName":"Burnett, Patrick (Farmers Insurance)","given_name":"Patrick","sur_name":"Burnett","organization":"Farmers Insurance","error":false},{"meeting_cd":"C3202001042310301","committee":"Insurance Committee","dttm":"April 23, 2001-10:30A","session":"77R","bill_name":"HB 955","bill_cd":"HB955","position":"Against","rbnt":false,"self":true,"fullWitnessName":"Cartright, Steve (Self and NAPA Auto Parts; CARE)","given_name":"Steve","sur_name":"Cartright","organization":"and NAPA Auto Parts; CARE","error":false},{"meeting_cd":"C3202001042310301","committee":"Insurance Committee","dttm":"April 23, 2001-10:30A","session":"77R","bill_name":"HB 955","bill_cd":"HB955","position":"Against","rbnt":false,"self":false,"fullWitnessName":"Floyd, Beaman (USAA)","given_name":"Beaman","sur_name":"Floyd","organization":"USAA","error":false},{"meeting_cd":"C3202001042310301","committee":"Insurance Committee","dttm":"April 23, 2001-10:30A","session":"77R","bill_name":"HB 955","bill_cd":"HB955","position":"Against","rbnt":false,"self":false,"fullWitnessName":"Geiger, Richard (Association of Fire and Casualty                   Companies in Texas)\r","given_name":"Richard","sur_name":"Geiger","organization":"Association of Fire and Casualty Companies in Texas","error":false},{"meeting_cd":"C3202001042310301","committee":"Insurance Committee","dttm":"April 23, 2001-10:30A","session":"77R","bill_name":"HB 955","bill_cd":"HB955","position":"Against","rbnt":false,"self":false,"fullWitnessName":"Huxel, Bob (Famers Insurance Group)","given_name":"Bob","sur_name":"Huxel","organization":"Famers Insurance Group","error":false},{"meeting_cd":"C3202001042310301","committee":"Insurance Committee","dttm":"April 23, 2001-10:30A","session":"77R","bill_name":"HB 956","bill_cd":"HB956","position":"For","rbnt":false,"self":true,"fullWitnessName":"Braddy, Lonnie Lee (Self)","given_name":"Lonnie Lee","sur_name":"Braddy","organization":"","error":false},{"meeting_cd":"C3202001042310301","committee":"Insurance Committee","dttm":"April 23, 2001-10:30A","session":"77R","bill_name":"HB 956","bill_cd":"HB956","position":"For","rbnt":false,"self":true,"fullWitnessName":"Day, Donald (Self)","given_name":"Donald","sur_name":"Day","organization":"","error":false},{"meeting_cd":"C3202001042310301","committee":"Insurance Committee","dttm":"April 23, 2001-10:30A","session":"77R","bill_name":"HB 956","bill_cd":"HB956","position":"For","rbnt":false,"self":false,"fullWitnessName":"Lloyd, Chuck (Texas Glass and Tinting)","given_name":"Chuck","sur_name":"Lloyd","organization":"Texas Glass and Tinting","error":false},{"meeting_cd":"C3202001042310301","committee":"Insurance Committee","dttm":"April 23, 2001-10:30A","session":"77R","bill_name":"HB 956","bill_cd":"HB956","position":"For","rbnt":false,"self":true,"fullWitnessName":"Prestridge, Jeanette (Self)","given_name":"Jeanette","sur_name":"Prestridge","organization":"","error":false},{"meeting_cd":"C3202001042310301","committee":"Insurance Committee","dttm":"April 23, 2001-10:30A","session":"77R","bill_name":"HB 956","bill_cd":"HB956","position":"For","rbnt":false,"self":true,"fullWitnessName":"Smalley, Roy (Self and Texas Lone Star Collision                   Association)\r","given_name":"Roy","sur_name":"Smalley","organization":"and Texas Lone Star Collision Association","error":false},{"meeting_cd":"C3202001042310301","committee":"Insurance Committee","dttm":"April 23, 2001-10:30A","session":"77R","bill_name":"HB 956","bill_cd":"HB956","position":"For","rbnt":false,"self":false,"fullWitnessName":"Walden, James (Direct Appraisal)","given_name":"James","sur_name":"Walden","organization":"Direct Appraisal","error":false},{"meeting_cd":"C3202001042310301","committee":"Insurance Committee","dttm":"April 23, 2001-10:30A","session":"77R","bill_name":"HB 956","bill_cd":"HB956","position":"Against","rbnt":false,"self":false,"fullWitnessName":"Burnett, Patrick (Farmers Insurance Group)","given_name":"Patrick","sur_name":"Burnett","organization":"Farmers Insurance Group","error":false},{"meeting_cd":"C3202001042310301","committee":"Insurance Committee","dttm":"April 23, 2001-10:30A","session":"77R","bill_name":"HB 956","bill_cd":"HB956","position":"Against","rbnt":false,"self":false,"fullWitnessName":"Burris, Jimmy Don (Herb's Paint & Body)","given_name":"Jimmy Don","sur_name":"Burris","organization":"Herb's Paint & Body","error":false},{"meeting_cd":"C3202001042310301","committee":"Insurance Committee","dttm":"April 23, 2001-10:30A","session":"77R","bill_name":"HB 956","bill_cd":"HB956","position":"Against","rbnt":false,"self":false,"fullWitnessName":"Floyd, Beaman (USAA)","given_name":"Beaman","sur_name":"Floyd","organization":"USAA","error":false},{"meeting_cd":"C3202001042310301","committee":"Insurance Committee","dttm":"April 23, 2001-10:30A","session":"77R","bill_name":"HB 956","bill_cd":"HB956","position":"Against","rbnt":false,"self":false,"fullWitnessName":"Geiger, Richard (Association of Fire & Casualty                   Companies in Texas)\r","given_name":"Richard","sur_name":"Geiger","organization":"Association of Fire & Casualty Companies in Texas","error":false},{"meeting_cd":"C3202001042310301","committee":"Insurance Committee","dttm":"April 23, 2001-10:30A","session":"77R","bill_name":"HB 956","bill_cd":"HB956","position":"Against","rbnt":false,"self":false,"fullWitnessName":"Gilbert, Bo (Independent Insurance Agents of Texas)","given_name":"Bo","sur_name":"Gilbert","organization":"Independent Insurance Agents of Texas","error":false},{"meeting_cd":"C3202001042310301","committee":"Insurance Committee","dttm":"April 23, 2001-10:30A","session":"77R","bill_name":"HB 956","bill_cd":"HB956","position":"Against","rbnt":false,"self":false,"fullWitnessName":"Huxel, Bob (Farmers Insurance Group)","given_name":"Bob","sur_name":"Huxel","organization":"Farmers Insurance Group","error":false},{"meeting_cd":"C3202001042310301","committee":"Insurance Committee","dttm":"April 23, 2001-10:30A","session":"77R","bill_name":"HB 1865","bill_cd":"HB1865","position":"For","rbnt":false,"self":true,"fullWitnessName":"Desmond, Robert (Self)","given_name":"Robert","sur_name":"Desmond","organization":"","error":false},{"meeting_cd":"C3202001042310301","committee":"Insurance Committee","dttm":"April 23, 2001-10:30A","session":"77R","bill_name":"HB 2019","bill_cd":"HB2019","position":"For","rbnt":false,"self":false,"fullWitnessName":"Walden, James (Direct Appraisal)","given_name":"James","sur_name":"Walden","organization":"Direct Appraisal","error":false},{"meeting_cd":"C3202001042310301","committee":"Insurance Committee","dttm":"April 23, 2001-10:30A","session":"77R","bill_name":"HB 2019","bill_cd":"HB2019","position":"Against","rbnt":false,"self":false,"fullWitnessName":"Geiger, Richard (Assoc of Fire & Casualty Co's in Texas)","given_name":"Richard","sur_name":"Geiger","organization":"Assoc of Fire & Casualty Co's in Texas","error":false},{"meeting_cd":"C3202001042310301","committee":"Insurance Committee","dttm":"April 23, 2001-10:30A","session":"77R","bill_name":"HB 2785","bill_cd":"HB2785","position":"Against","rbnt":false,"self":false,"fullWitnessName":"McGiffert, Lisa (Consumers Union)","given_name":"Lisa","sur_name":"McGiffert","organization":"Consumers Union","error":false},{"meeting_cd":"C3202001042310301","committee":"Insurance Committee","dttm":"April 23, 2001-10:30A","session":"77R","bill_name":"HB 3010","bill_cd":"HB3010","position":"For","rbnt":false,"self":false,"fullWitnessName":"Dacso, Sheryl (Rural Community Health System)","given_name":"Sheryl","sur_name":"Dacso","organization":"Rural Community Health System","error":false},{"meeting_cd":"C3202001042310301","committee":"Insurance Committee","dttm":"April 23, 2001-10:30A","session":"77R","bill_name":"HB 3010","bill_cd":"HB3010","position":"For","rbnt":false,"self":false,"fullWitnessName":"McGiffert, Lisa (Consumers Union)","given_name":"Lisa","sur_name":"McGiffert","organization":"Consumers Union","error":false},{"meeting_cd":"C3202001042310301","committee":"Insurance Committee","dttm":"April 23, 2001-10:30A","session":"77R","bill_name":"HB 3010","bill_cd":"HB3010","position":"For","rbnt":false,"self":false,"fullWitnessName":"Mueller, M.D., Thomas (Rural Community Health System)","given_name":"M.D., Thomas","sur_name":"Mueller","organization":"Rural Community Health System","error":false},{"meeting_cd":"C3202001042310301","committee":"Insurance Committee","dttm":"April 23, 2001-10:30A","session":"77R","bill_name":"HB 3010","bill_cd":"HB3010","position":"For","rbnt":false,"self":false,"fullWitnessName":"Rummel, Leah (Texas Association of Health Plans)","given_name":"Leah","sur_name":"Rummel","organization":"Texas Association of Health Plans","error":false},{"meeting_cd":"C3202001042310301","committee":"Insurance Committee","dttm":"April 23, 2001-10:30A","session":"77R","bill_name":"HB 3010","bill_cd":"HB3010","position":"For","rbnt":false,"self":false,"fullWitnessName":"Wallace, B.R. \"Skipper\" (Rural Community Health System                   of Texas)\r","given_name":"B.R. \"Skipper\"","sur_name":"Wallace","organization":"Rural Community Health System of Texas","error":false},{"meeting_cd":"C3202001042310301","committee":"Insurance Committee","dttm":"April 23, 2001-10:30A","session":"77R","bill_name":"HB 3010","bill_cd":"HB3010","position":"For","rbnt":false,"self":false,"fullWitnessName":"Yeary, John (Rural Community Health System)","given_name":"John","sur_name":"Yeary","organization":"Rural Community Health System","error":false},{"meeting_cd":"C3202001042310301","committee":"Insurance Committee","dttm":"April 23, 2001-10:30A","session":"77R","bill_name":"HB 3328","bill_cd":"HB3328","position":"For","rbnt":false,"self":false,"fullWitnessName":"Davis, Will (Texas Association of Life and Health                   Insurers)\r","given_name":"Will","sur_name":"Davis","organization":"Texas Association of Life and Health Insurers","error":false},{"meeting_cd":"C3202001042310301","committee":"Insurance Committee","dttm":"April 23, 2001-10:30A","session":"77R","bill_name":"HB 3328","bill_cd":"HB3328","position":"On","rbnt":false,"self":false,"fullWitnessName":"McGiffert, Lisa (Consumers Union)","given_name":"Lisa","sur_name":"McGiffert","organization":"Consumers Union","error":false},{"meeting_cd":"C3202001042310301","committee":"Insurance Committee","dttm":"April 23, 2001-10:30A","session":"77R","bill_name":"HB 3630","bill_cd":"HB3630","position":"For","rbnt":false,"self":false,"fullWitnessName":"Camacho, Jose (Texas Association of Community Health                   Centers, Inc.)\r","given_name":"Jose","sur_name":"Camacho","organization":"Texas Association of Community Health Centers, Inc.","error":false},{"meeting_cd":"C3202001042310301","committee":"Insurance Committee","dttm":"April 23, 2001-10:30A","session":"77R","bill_name":"SB 327","bill_cd":"SB327","position":"On","rbnt":false,"self":false,"fullWitnessName":"Davis, Mike (Texas Department of Insurance/State Fire                   Marshal)\r","given_name":"Mike","sur_name":"Davis","organization":"Texas Department of Insurance/State Fire Marshal","error":false},{"meeting_cd":"C3202001042310301","committee":"Insurance Committee","dttm":"April 23, 2001-10:30A","session":"77R","bill_name":"SB 601","bill_cd":"SB601","position":"For","rbnt":false,"self":false,"fullWitnessName":"Adamek, Thomas (Stonehenge Capital Corporation)","given_name":"Thomas","sur_name":"Adamek","organization":"Stonehenge Capital Corporation","error":false},{"meeting_cd":"C3202001042310301","committee":"Insurance Committee","dttm":"April 23, 2001-10:30A","session":"77R","bill_name":"SB 601","bill_cd":"SB601","position":"For","rbnt":false,"self":true,"fullWitnessName":"Dooley, Dave (Self)","given_name":"Dave","sur_name":"Dooley","organization":"","error":false},{"meeting_cd":"C3202001042310301","committee":"Insurance Committee","dttm":"April 23, 2001-10:30A","session":"77R","bill_name":"SB 601","bill_cd":"SB601","position":"For","rbnt":false,"self":false,"fullWitnessName":"Thomas, Phil (Growth Capital Alliance)","given_name":"Phil","sur_name":"Thomas","organization":"Growth Capital Alliance","error":false},{"meeting_cd":"C3202001042310301","committee":"Insurance Committee","dttm":"April 23, 2001-10:30A","session":"77R","bill_name":"SB 601","bill_cd":"SB601","position":"Against","rbnt":false,"self":false,"fullWitnessName":"Thompson, Jay (Prudential Insurance Company)","given_name":"Jay","sur_name":"Thompson","organization":"Prudential Insurance Company","error":false},{"meeting_cd":"C3202001042310301","committee":"Insurance Committee","dttm":"April 23, 2001-10:30A","session":"77R","bill_name":"SB 804","bill_cd":"SB804","position":"For","rbnt":false,"self":false,"fullWitnessName":"McGiffert, Lisa (Consumers Union)","given_name":"Lisa","sur_name":"McGiffert","organization":"Consumers Union","error":false},{"meeting_cd":"C3202001042310301","committee":"Insurance Committee","dttm":"April 23, 2001-10:30A","session":"77R","bill_name":"SB 992","bill_cd":"SB992","position":"For","rbnt":false,"self":false,"fullWitnessName":"Pollard, Mike (Texas Association of Life and Health                   Insurers)\r","given_name":"Mike","sur_name":"Pollard","organization":"Texas Association of Life and Health Insurers","error":false},{"meeting_cd":"C3202001042310301","committee":"Insurance Committee","dttm":"April 23, 2001-10:30A","session":"77R","bill_name":"SB 1143","bill_cd":"SB1143","position":"For","rbnt":false,"self":false,"fullWitnessName":"Rummel, Leah (Texas Association of Health Plans)","given_name":"Leah","sur_name":"Rummel","organization":"Texas Association of Health Plans","error":false}]