[{"meeting_cd":"C2802000061910001","committee":"General Investigating Committee","dttm":"June 19, 2000-10:00A","session":"","bill_name":"","bill_cd":"","position":"","rbnt":false,"self":true,"fullWitnessName":"Interim Charges    For:      Serna, Santos (Self)\r","given_name":"Santos","sur_name":"Interim Charges For: Serna","organization":"","error":false},{"meeting_cd":"C2802000061910001","committee":"General Investigating Committee","dttm":"June 19, 2000-10:00A","session":"","bill_name":"","bill_cd":"","position":"Against","rbnt":false,"self":true,"fullWitnessName":"Flores, David (Self and Southwest Consulting)","given_name":"David","sur_name":"Flores","organization":"and Southwest Consulting","error":false},{"meeting_cd":"C2802000061910001","committee":"General Investigating Committee","dttm":"June 19, 2000-10:00A","session":"","bill_name":"","bill_cd":"","position":"On","rbnt":false,"self":false,"fullWitnessName":"Felkner, Jerry (Texas Department of Health)","given_name":"Jerry","sur_name":"Felkner","organization":"Texas Department of Health","error":false},{"meeting_cd":"C2802000061910001","committee":"General Investigating Committee","dttm":"June 19, 2000-10:00A","session":"","bill_name":"","bill_cd":"","position":"On","rbnt":false,"self":false,"fullWitnessName":"LeBrun, Aurora (Texas Health and Human Services                   Commission)\r","given_name":"Aurora","sur_name":"LeBrun","organization":"Texas Health and Human Services Commission","error":false},{"meeting_cd":"C2802000061910001","committee":"General Investigating Committee","dttm":"June 19, 2000-10:00A","session":"","bill_name":"","bill_cd":"","position":"On","rbnt":false,"self":true,"fullWitnessName":"Olson, Robert (Self)","given_name":"Robert","sur_name":"Olson","organization":"","error":false},{"meeting_cd":"C2802000061910001","committee":"General Investigating Committee","dttm":"June 19, 2000-10:00A","session":"","bill_name":"","bill_cd":"","position":"On","rbnt":false,"self":true,"fullWitnessName":"Seiler, Harold (Self)","given_name":"Harold","sur_name":"Seiler","organization":"","error":false},{"meeting_cd":"C2802000061910001","committee":"General Investigating Committee","dttm":"June 19, 2000-10:00A","session":"","bill_name":"","bill_cd":"","position":"On","rbnt":false,"self":true,"fullWitnessName":"Shaner, Karl (Self)","given_name":"Karl","sur_name":"Shaner","organization":"","error":false},{"meeting_cd":"C2802000061910001","committee":"General Investigating Committee","dttm":"June 19, 2000-10:00A","session":"","bill_name":"","bill_cd":"","position":"On","rbnt":false,"self":true,"fullWitnessName":"Steinhauer, William (Self)","given_name":"William","sur_name":"Steinhauer","organization":"","error":false}]