[{"meeting_cd":"C3951997022508001","committee":"Pensions and Investments Committee","dttm":"February 25, 1997-8:00A","session":"75R","bill_name":"HB 336","bill_cd":"HB336","position":"For","rbnt":false,"self":false,"fullWitnessName":"Williams, Herbert M. (Conroe Fire Ret. Fund)","given_name":"Herbert M.","sur_name":"Williams","organization":"Conroe Fire Ret. Fund","error":false},{"meeting_cd":"C3951997022508001","committee":"Pensions and Investments Committee","dttm":"February 25, 1997-8:00A","session":"75R","bill_name":"HB 336","bill_cd":"HB336","position":"On","rbnt":false,"self":false,"fullWitnessName":"Campbell, Helen (Firefighters Pension Cm)","given_name":"Helen","sur_name":"Campbell","organization":"Firefighters Pension Cm","error":false},{"meeting_cd":"C3951997022508001","committee":"Pensions and Investments Committee","dttm":"February 25, 1997-8:00A","session":"75R","bill_name":"HB 336","bill_cd":"HB336","position":"For","rbnt":true,"self":false,"fullWitnessName":"Bailey, Ken (Assoc. of Firefighters)","given_name":"Ken","sur_name":"Bailey","organization":"Assoc. of Firefighters","error":false},{"meeting_cd":"C3951997022508001","committee":"Pensions and Investments Committee","dttm":"February 25, 1997-8:00A","session":"75R","bill_name":"HB 336","bill_cd":"HB336","position":"For","rbnt":true,"self":false,"fullWitnessName":"Epley, Robert (Consulting actuary)","given_name":"Robert","sur_name":"Epley","organization":"Consulting actuary","error":false},{"meeting_cd":"C3951997022508001","committee":"Pensions and Investments Committee","dttm":"February 25, 1997-8:00A","session":"75R","bill_name":"HB 336","bill_cd":"HB336","position":"For","rbnt":true,"self":false,"fullWitnessName":"Hlavaty, Patrick (Firemen/F-Marshall Assn)","given_name":"Patrick","sur_name":"Hlavaty","organization":"Firemen/F-Marshall Assn","error":false},{"meeting_cd":"C3951997022508001","committee":"Pensions and Investments Committee","dttm":"February 25, 1997-8:00A","session":"75R","bill_name":"HB 336","bill_cd":"HB336","position":"For","rbnt":true,"self":false,"fullWitnessName":"Littlejohn, Alva (Lubbock Fire Ret. Fund)","given_name":"Alva","sur_name":"Littlejohn","organization":"Lubbock Fire Ret. Fund","error":false},{"meeting_cd":"C3951997022508001","committee":"Pensions and Investments Committee","dttm":"February 25, 1997-8:00A","session":"75R","bill_name":"HB 336","bill_cd":"HB336","position":"For","rbnt":true,"self":false,"fullWitnessName":"Shanklin, Bill (Georgetown Fire Dept.)","given_name":"Bill","sur_name":"Shanklin","organization":"Georgetown Fire Dept.","error":false},{"meeting_cd":"C3951997022508001","committee":"Pensions and Investments Committee","dttm":"February 25, 1997-8:00A","session":"75R","bill_name":"HB 336","bill_cd":"HB336","position":"For","rbnt":true,"self":false,"fullWitnessName":"Sullivan, RF (Firemen/F-Marshall Assn)","given_name":"RF","sur_name":"Sullivan","organization":"Firemen/F-Marshall Assn","error":false},{"meeting_cd":"C3951997022508001","committee":"Pensions and Investments Committee","dttm":"February 25, 1997-8:00A","session":"75R","bill_name":"HB 336","bill_cd":"HB336","position":"On","rbnt":true,"self":false,"fullWitnessName":"Horwitz, Rita (Pension Review Bd)","given_name":"Rita","sur_name":"Horwitz","organization":"Pension Review Bd","error":false},{"meeting_cd":"C3951997022508001","committee":"Pensions and Investments Committee","dttm":"February 25, 1997-8:00A","session":"75R","bill_name":"HB 336","bill_cd":"HB336","position":"On","rbnt":true,"self":false,"fullWitnessName":"May, Robert (Consulting Actuary)","given_name":"Robert","sur_name":"May","organization":"Consulting Actuary","error":false},{"meeting_cd":"C3951997022508001","committee":"Pensions and Investments Committee","dttm":"February 25, 1997-8:00A","session":"75R","bill_name":"HB 735","bill_cd":"HB735","position":"For","rbnt":false,"self":false,"fullWitnessName":"Epley, Robert (Consulting Actuary)","given_name":"Robert","sur_name":"Epley","organization":"Consulting Actuary","error":false},{"meeting_cd":"C3951997022508001","committee":"Pensions and Investments Committee","dttm":"February 25, 1997-8:00A","session":"75R","bill_name":"HB 735","bill_cd":"HB735","position":"For","rbnt":false,"self":false,"fullWitnessName":"Littlejohn, Alva (Lubbock Fire Ret. Fund)","given_name":"Alva","sur_name":"Littlejohn","organization":"Lubbock Fire Ret. Fund","error":false},{"meeting_cd":"C3951997022508001","committee":"Pensions and Investments Committee","dttm":"February 25, 1997-8:00A","session":"75R","bill_name":"HB 735","bill_cd":"HB735","position":"For","rbnt":true,"self":false,"fullWitnessName":"Bailey, Ken (Assn. of Firefighters)","given_name":"Ken","sur_name":"Bailey","organization":"Assn. of Firefighters","error":false},{"meeting_cd":"C3951997022508001","committee":"Pensions and Investments Committee","dttm":"February 25, 1997-8:00A","session":"75R","bill_name":"HB 735","bill_cd":"HB735","position":"For","rbnt":true,"self":false,"fullWitnessName":"Hlavaty, Patrick (Firemen/f-marshall Assn)","given_name":"Patrick","sur_name":"Hlavaty","organization":"Firemen/f-marshall Assn","error":false},{"meeting_cd":"C3951997022508001","committee":"Pensions and Investments Committee","dttm":"February 25, 1997-8:00A","session":"75R","bill_name":"HB 735","bill_cd":"HB735","position":"For","rbnt":true,"self":false,"fullWitnessName":"Shanklin, Bill (Georgetown Fire Dept.)","given_name":"Bill","sur_name":"Shanklin","organization":"Georgetown Fire Dept.","error":false},{"meeting_cd":"C3951997022508001","committee":"Pensions and Investments Committee","dttm":"February 25, 1997-8:00A","session":"75R","bill_name":"HB 735","bill_cd":"HB735","position":"For","rbnt":true,"self":false,"fullWitnessName":"Sullivan, R.F. (Firemen/F-Marshall Assn)","given_name":"R.F.","sur_name":"Sullivan","organization":"Firemen/F-Marshall Assn","error":false},{"meeting_cd":"C3951997022508001","committee":"Pensions and Investments Committee","dttm":"February 25, 1997-8:00A","session":"75R","bill_name":"HB 735","bill_cd":"HB735","position":"For","rbnt":true,"self":false,"fullWitnessName":"Williams, Herbert (Conroe Fire Ret. Fund)","given_name":"Herbert","sur_name":"Williams","organization":"Conroe Fire Ret. Fund","error":false},{"meeting_cd":"C3951997022508001","committee":"Pensions and Investments Committee","dttm":"February 25, 1997-8:00A","session":"75R","bill_name":"HB 735","bill_cd":"HB735","position":"On","rbnt":true,"self":false,"fullWitnessName":"Campbell, Helen (Firefighter Pension Com)","given_name":"Helen","sur_name":"Campbell","organization":"Firefighter Pension Com","error":false},{"meeting_cd":"C3951997022508001","committee":"Pensions and Investments Committee","dttm":"February 25, 1997-8:00A","session":"75R","bill_name":"HB 735","bill_cd":"HB735","position":"On","rbnt":true,"self":false,"fullWitnessName":"Horwitz, Rita (Pension Review Bd.)","given_name":"Rita","sur_name":"Horwitz","organization":"Pension Review Bd.","error":false},{"meeting_cd":"C3951997022508001","committee":"Pensions and Investments Committee","dttm":"February 25, 1997-8:00A","session":"75R","bill_name":"HB 735","bill_cd":"HB735","position":"On","rbnt":true,"self":false,"fullWitnessName":"May, Robert (Consulting Actuary)","given_name":"Robert","sur_name":"May","organization":"Consulting Actuary","error":false},{"meeting_cd":"C3951997022508001","committee":"Pensions and Investments Committee","dttm":"February 25, 1997-8:00A","session":"75R","bill_name":"HB 803","bill_cd":"HB803","position":"For","rbnt":false,"self":false,"fullWitnessName":"Rice, Joe (Volunteer FF Pension Cm)","given_name":"Joe","sur_name":"Rice","organization":"Volunteer FF Pension Cm","error":false},{"meeting_cd":"C3951997022508001","committee":"Pensions and Investments Committee","dttm":"February 25, 1997-8:00A","session":"75R","bill_name":"HB 803","bill_cd":"HB803","position":"For","rbnt":false,"self":false,"fullWitnessName":"Shanklin, Bill (Georgetown Fire Dept.)","given_name":"Bill","sur_name":"Shanklin","organization":"Georgetown Fire Dept.","error":false},{"meeting_cd":"C3951997022508001","committee":"Pensions and Investments Committee","dttm":"February 25, 1997-8:00A","session":"75R","bill_name":"HB 803","bill_cd":"HB803","position":"For","rbnt":true,"self":false,"fullWitnessName":"Bailey, Ken (Assn of Firefighters)","given_name":"Ken","sur_name":"Bailey","organization":"Assn of Firefighters","error":false},{"meeting_cd":"C3951997022508001","committee":"Pensions and Investments Committee","dttm":"February 25, 1997-8:00A","session":"75R","bill_name":"HB 803","bill_cd":"HB803","position":"For","rbnt":true,"self":false,"fullWitnessName":"Epley, Robert (Consulting Actuary)","given_name":"Robert","sur_name":"Epley","organization":"Consulting Actuary","error":false},{"meeting_cd":"C3951997022508001","committee":"Pensions and Investments Committee","dttm":"February 25, 1997-8:00A","session":"75R","bill_name":"HB 803","bill_cd":"HB803","position":"For","rbnt":true,"self":false,"fullWitnessName":"Hlavaty, Patrick (Firemen/F-Marshall Assn)","given_name":"Patrick","sur_name":"Hlavaty","organization":"Firemen/F-Marshall Assn","error":false},{"meeting_cd":"C3951997022508001","committee":"Pensions and Investments Committee","dttm":"February 25, 1997-8:00A","session":"75R","bill_name":"HB 803","bill_cd":"HB803","position":"For","rbnt":true,"self":false,"fullWitnessName":"Sullivan, RF (Firemen/F-Marshall Assn)","given_name":"RF","sur_name":"Sullivan","organization":"Firemen/F-Marshall Assn","error":false},{"meeting_cd":"C3951997022508001","committee":"Pensions and Investments Committee","dttm":"February 25, 1997-8:00A","session":"75R","bill_name":"HB 803","bill_cd":"HB803","position":"For","rbnt":true,"self":false,"fullWitnessName":"Williams, Herbert (Conroe Fire Ret. Fund)","given_name":"Herbert","sur_name":"Williams","organization":"Conroe Fire Ret. Fund","error":false},{"meeting_cd":"C3951997022508001","committee":"Pensions and Investments Committee","dttm":"February 25, 1997-8:00A","session":"75R","bill_name":"HB 803","bill_cd":"HB803","position":"On","rbnt":true,"self":false,"fullWitnessName":"Campbell, Helen (FF Pension Commission)","given_name":"Helen","sur_name":"Campbell","organization":"FF Pension Commission","error":false},{"meeting_cd":"C3951997022508001","committee":"Pensions and Investments Committee","dttm":"February 25, 1997-8:00A","session":"75R","bill_name":"HB 803","bill_cd":"HB803","position":"On","rbnt":true,"self":false,"fullWitnessName":"Horwitz, Rita (Pension Review Bd.)","given_name":"Rita","sur_name":"Horwitz","organization":"Pension Review Bd.","error":false},{"meeting_cd":"C3951997022508001","committee":"Pensions and Investments Committee","dttm":"February 25, 1997-8:00A","session":"75R","bill_name":"HB 1113","bill_cd":"HB1113","position":"On","rbnt":false,"self":false,"fullWitnessName":"Anderson, Gary (TMRS)","given_name":"Gary","sur_name":"Anderson","organization":"TMRS","error":false},{"meeting_cd":"C3951997022508001","committee":"Pensions and Investments Committee","dttm":"February 25, 1997-8:00A","session":"75R","bill_name":"HB 1113","bill_cd":"HB1113","position":"For","rbnt":true,"self":false,"fullWitnessName":"Clark, Mark (CLEAT)","given_name":"Mark","sur_name":"Clark","organization":"CLEAT","error":false},{"meeting_cd":"C3951997022508001","committee":"Pensions and Investments Committee","dttm":"February 25, 1997-8:00A","session":"75R","bill_name":"HB 1113","bill_cd":"HB1113","position":"For","rbnt":true,"self":false,"fullWitnessName":"Shanklin, Bill (Georgetown Fire Dept.)","given_name":"Bill","sur_name":"Shanklin","organization":"Georgetown Fire Dept.","error":false},{"meeting_cd":"C3951997022508001","committee":"Pensions and Investments Committee","dttm":"February 25, 1997-8:00A","session":"75R","bill_name":"HB 1113","bill_cd":"HB1113","position":"For","rbnt":true,"self":false,"fullWitnessName":"Williams, Herbert (Conroe Fire Ret. Fund)","given_name":"Herbert","sur_name":"Williams","organization":"Conroe Fire Ret. Fund","error":false},{"meeting_cd":"C3951997022508001","committee":"Pensions and Investments Committee","dttm":"February 25, 1997-8:00A","session":"75R","bill_name":"HB 1113","bill_cd":"HB1113","position":"On","rbnt":true,"self":false,"fullWitnessName":"Beuhner, Kathleen (TMRS)","given_name":"Kathleen","sur_name":"Beuhner","organization":"TMRS","error":false},{"meeting_cd":"C3951997022508001","committee":"Pensions and Investments Committee","dttm":"February 25, 1997-8:00A","session":"75R","bill_name":"HB 1113","bill_cd":"HB1113","position":"On","rbnt":true,"self":false,"fullWitnessName":"Davis, Eric W. (TMRS)","given_name":"Eric W.","sur_name":"Davis","organization":"TMRS","error":false},{"meeting_cd":"C3951997022508001","committee":"Pensions and Investments Committee","dttm":"February 25, 1997-8:00A","session":"75R","bill_name":"HB 1113","bill_cd":"HB1113","position":"On","rbnt":true,"self":false,"fullWitnessName":"Horwitz, Rita (Pension Review Bd.)","given_name":"Rita","sur_name":"Horwitz","organization":"Pension Review Bd.","error":false},{"meeting_cd":"C3951997022508001","committee":"Pensions and Investments Committee","dttm":"February 25, 1997-8:00A","session":"75R","bill_name":"HB 1113","bill_cd":"HB1113","position":"On","rbnt":true,"self":false,"fullWitnessName":"Joyner, Leon (Rocky) (TMRS)","given_name":"Leon  (TMRS)","sur_name":"Joyner","organization":"Rocky","error":false},{"meeting_cd":"C3951997022508001","committee":"Pensions and Investments Committee","dttm":"February 25, 1997-8:00A","session":"75R","bill_name":"HB 1113","bill_cd":"HB1113","position":"On","rbnt":true,"self":false,"fullWitnessName":"Kendall, Terrence (TMRS)","given_name":"Terrence","sur_name":"Kendall","organization":"TMRS","error":false},{"meeting_cd":"C3951997022508001","committee":"Pensions and Investments Committee","dttm":"February 25, 1997-8:00A","session":"75R","bill_name":"HCR 29","bill_cd":"HCR29","position":"On","rbnt":false,"self":false,"fullWitnessName":"Campbell, Helen (Firefighter Pension Com)","given_name":"Helen","sur_name":"Campbell","organization":"Firefighter Pension Com","error":false},{"meeting_cd":"C3951997022508001","committee":"Pensions and Investments Committee","dttm":"February 25, 1997-8:00A","session":"75R","bill_name":"HCR 29","bill_cd":"HCR29","position":"For","rbnt":true,"self":false,"fullWitnessName":"Bailey, Ken (Assn. of Firefighters)","given_name":"Ken","sur_name":"Bailey","organization":"Assn. of Firefighters","error":false},{"meeting_cd":"C3951997022508001","committee":"Pensions and Investments Committee","dttm":"February 25, 1997-8:00A","session":"75R","bill_name":"HCR 29","bill_cd":"HCR29","position":"For","rbnt":true,"self":false,"fullWitnessName":"Epley, Robert (Consulting Actuary)","given_name":"Robert","sur_name":"Epley","organization":"Consulting Actuary","error":false},{"meeting_cd":"C3951997022508001","committee":"Pensions and Investments Committee","dttm":"February 25, 1997-8:00A","session":"75R","bill_name":"HCR 29","bill_cd":"HCR29","position":"For","rbnt":true,"self":false,"fullWitnessName":"Hlavaty, Patrick (Firemen/F-marshall assn)","given_name":"Patrick","sur_name":"Hlavaty","organization":"Firemen/F-marshall assn","error":false},{"meeting_cd":"C3951997022508001","committee":"Pensions and Investments Committee","dttm":"February 25, 1997-8:00A","session":"75R","bill_name":"HCR 29","bill_cd":"HCR29","position":"For","rbnt":true,"self":false,"fullWitnessName":"Rice, Joe (Volunteer Fire Pension)","given_name":"Joe","sur_name":"Rice","organization":"Volunteer Fire Pension","error":false},{"meeting_cd":"C3951997022508001","committee":"Pensions and Investments Committee","dttm":"February 25, 1997-8:00A","session":"75R","bill_name":"HCR 29","bill_cd":"HCR29","position":"For","rbnt":true,"self":false,"fullWitnessName":"Shanklin, Bill (Georgetown Fire Dept.)","given_name":"Bill","sur_name":"Shanklin","organization":"Georgetown Fire Dept.","error":false},{"meeting_cd":"C3951997022508001","committee":"Pensions and Investments Committee","dttm":"February 25, 1997-8:00A","session":"75R","bill_name":"HCR 29","bill_cd":"HCR29","position":"For","rbnt":true,"self":false,"fullWitnessName":"Sullivan, RF (Firemen/F-marshall Assn)","given_name":"RF","sur_name":"Sullivan","organization":"Firemen/F-marshall Assn","error":false},{"meeting_cd":"C3951997022508001","committee":"Pensions and Investments Committee","dttm":"February 25, 1997-8:00A","session":"75R","bill_name":"HCR 29","bill_cd":"HCR29","position":"On","rbnt":true,"self":false,"fullWitnessName":"Horwitz, Rita (Pension Rev. Board)","given_name":"Rita","sur_name":"Horwitz","organization":"Pension Rev. Board","error":false}]